{
  "url": "https://agenciabrasil.ebc.com.br/economia/noticia/2024-12/dolar-sobe-para-r-603-apesar-de-intervencao-do-banco-central",
  "titulo": "Dólar sobe para R$ 6,03, apesar de intervenção do Banco Central",
  "descricao": "Bolsa teve queda de 1,13% e atingiu menor nível em duas semanas. Tanto fatores internos quanto externos influenciaram o mercado.",
  "texto": "Num dia de tensões no mercado financeiro, o dólar subiu, apesar de o Banco Central (BC) ter intervindo no câmbio pela segunda vez em dois dias. A bolsa caiu mais uma vez e atingiu o menor nível em duas semanas.\n\n\nO dólar comercial encerrou esta sexta-feira (13) vendido a R$ 6,035, com alta de R$ 0,026 (+0,43%). A cotação chegou a abrir em baixa, mas inverteu o movimento e passou a subir ainda durante a manhã. A moeda desacelerou no meio da tarde, após o \nBC vender US$ 845 milhões das reservas internacionais\n. Mesmo assim, permaneceu acima de R$ 6.\n\n\nO mercado de ações teve um dia mais pessimista. Em queda pela segunda vez seguida, o índice Ibovespa, da B3, fechou aos 124.612 pontos, com recuo de 1,13%. O indicador está no menor nível desde 28 de novembro.\n\n\nTanto fatores internos como externos influenciaram o mercado. No exterior, o dólar subiu nesta sexta-feira, principalmente durante a tarde, especialmente perante aplicações financeiras tradicionais, como o ouro.\n\n\nNo entanto, o cenário doméstico predominou, com a desconfiança de que o Congresso desidratará o pacote de corte de gastos do governo. A votação depende da liberação de emendas parlamentares e corre contra o tempo, com o Parlamento entrando em recesso no fim da próxima semana.\n\n\n*Com informações da Reuters\n\n\n\n\n\n\nRelacionadas\n\n\n\n\n\n\n\n\n\n\n\n                    BC vende US$ 845 mi das reservas internacionais para segurar dólar",
  "data": "2024-12-13T22:26:00-03:00"
}